humanity/__init__.py
humanity/humd.py
humanity/indexes.py
humanity/main.py
humanity-3.0.10.dist-info/DESCRIPTION.rst
humanity-3.0.10.dist-info/METADATA
humanity-3.0.10.dist-info/RECORD
humanity-3.0.10.dist-info/WHEEL
humanity-3.0.10.dist-info/metadata.json
humanity-3.0.10.dist-info/top_level.txt
