Metadata-Version: 2.0
Name: humanity
Version: 3.0.10
Summary: Module for newbies, changes start index from 0 to 1
Home-page: https://github.com/vlad1777d/humanity
Author: vlad1777d
Author-email: naumovvladislav@mail.ru
License: UNKNOWN
Platform: UNKNOWN
